chipdriver/NpcapHelper.exe
chipdriver/Packet.dll
chipdriver/WlanHelper.exe
chipdriver/__init__.py
chipdriver/adcdriver.cp312-win_amd64.pyd
chipdriver/awgdriver.cp312-win_amd64.pyd
chipdriver/chipqremote.cp312-win_amd64.pyd
chipdriver/hpdcdriver.cp312-win_amd64.pyd
chipdriver/l_hpdcdriver.cp312-win_amd64.pyd
chipdriver/pawgdriver.cp312-win_amd64.pyd
chipdriver/test_pawg.cp312-win_amd64.pyd
chipdriver/wpcap.dll
chipdriver/adc/__init__.py
chipdriver/adc/adc_data.cp312-win_amd64.pyd
chipdriver/adc/adc_feedback.cp312-win_amd64.pyd
chipdriver/adc/adc_mixtable.cp312-win_amd64.pyd
chipdriver/adc/adc_parameter.cp312-win_amd64.pyd
chipdriver/adc/adc_readback.cp312-win_amd64.pyd
chipdriver/adc/adc_registry.cp312-win_amd64.pyd
chipdriver/adc/chipadc.cp312-win_amd64.pyd
chipdriver/awg/__init__.py
chipdriver/awg/chipfpga.cp312-win_amd64.pyd
chipdriver/awg/dds.cp312-win_amd64.pyd
chipdriver/awg/firfilter.cp312-win_amd64.pyd
chipdriver/awg/iirfilter.cp312-win_amd64.pyd
chipdriver/awg/parameter.cp312-win_amd64.pyd
chipdriver/awg/pulsewidth.cp312-win_amd64.pyd
chipdriver/awg/registry.cp312-win_amd64.pyd
chipdriver/filter/__init__.py
chipdriver/filter/chipfilter.cp312-win_amd64.pyd
chipdriver/hpdc/__init__.py
chipdriver/hpdc/chiphpdc.cp312-win_amd64.pyd
chipdriver/hpdc/chiphpdc_old.cp312-win_amd64.pyd
chipdriver/hpdc/hpdc_editor.cp312-win_amd64.pyd
chipdriver/hpdc/hpdc_editor_old.cp312-win_amd64.pyd
chipdriver/hpdc/hpdc_registry.cp312-win_amd64.pyd
chipdriver/hpdc/hpdc_registry_old.cp312-win_amd64.pyd
chipdriver/hpdc/hpdc_reset.cp312-win_amd64.pyd
chipdriver/hpdc/operation_table.cp312-win_amd64.pyd
chipdriver/infrastructure/ChipLogHandlers.cp312-win_amd64.pyd
chipdriver/infrastructure/__init__.py
chipdriver/infrastructure/axidma.cp312-win_amd64.pyd
chipdriver/infrastructure/basedriver.cp312-win_amd64.pyd
chipdriver/infrastructure/basesocket.cp312-win_amd64.pyd
chipdriver/infrastructure/config.cp312-win_amd64.pyd
chipdriver/infrastructure/generator.cp312-win_amd64.pyd
chipdriver-1.17.13.dist-info/METADATA
chipdriver-1.17.13.dist-info/WHEEL
chipdriver-1.17.13.dist-info/top_level.txt
chipdriver-1.17.13.dist-info/RECORD
